exetera/__init__.py
exetera/_version.py
exetera/bin/__init__.py
exetera/bin/dataset_parameters.py
exetera/bin/exetera.py
exetera/bin/exetera_perf_tests.py
exetera/bin/journal_test.py
exetera/bin/journaling_prototype.py
exetera/bin/journalling_prototype_import.py
exetera/core/__init__.py
exetera/core/abstract_types.py
exetera/core/csv_reader_speedup.py
exetera/core/data_writer.py
exetera/core/dataframe.py
exetera/core/dataset.py
exetera/core/fields.py
exetera/core/indexed_array.py
exetera/core/journal.py
exetera/core/operations.py
exetera/core/session.py
exetera/core/utils.py
exetera/core/validation.py
exetera/io/__init__.py
exetera/io/field_importers.py
exetera/io/importer.py
exetera/io/load_schema.py
exetera/io/parsers.py
exetera/processing/__init__.py
exetera/processing/date_time_helpers.py
exetera/processing/numpy_buffer.py
exetera-0.6.0.dist-info/LICENSE.txt
exetera-0.6.0.dist-info/METADATA
exetera-0.6.0.dist-info/WHEEL
exetera-0.6.0.dist-info/entry_points.txt
exetera-0.6.0.dist-info/top_level.txt
exetera-0.6.0.dist-info/RECORD
