Metadata-Version: 2.1
Name: exetera
Version: 0.6.0
Summary: High-volume key-value store and analytics, based on hdf5
Home-page: https://github.com/kcl-bmeis/ExeTera
Author-email: Ben Murray <benjamin.murray@kcl.ac.uk>
License: Apache 2.0 License, see LICENSE.txt
Project-URL: homepage, https://github.com/kcl-bmeis/ExeTera
Platform: UNKNOWN
Requires-Python: >=3.7
License-File: LICENSE.txt
Requires-Dist: numpy
Requires-Dist: pandas
Requires-Dist: h5py
Requires-Dist: numba
Requires-Dist: parameterized
